popdf/__init__.py
popdf/api/__init__.py
popdf/api/pdf.py
popdf/core/Batch_PDFType.py
popdf/core/PDFType.py
popdf/core/__init__.py
popdf/lib/__init__.py
popdf/lib/decrypt4pdf_utils.py
popdf/lib/del4pdf_utils.py
popdf/lib/encrypt4pdf_utils.py
popdf/lib/pdf2docx_utils.py
popdf/lib/pdf2imgs_utils.py
popdf/lib/pdf_exceptions.py
popdf/lib/pdfdecrypt_utils.py
popdf/lib/split4pdf_utils.py
popdf/lib/txt2pdf_utils.py
popdf/lib/pdf/__init__.py
popdf/lib/pdf/add_watermark_service.py
tests/__init__.py
tests/test_code/__init__.py
tests/test_code/test_dev.py
tests/test_code/test_pdf.py
popdf-1.0.7.dist-info/LICENSE
popdf-1.0.7.dist-info/METADATA
popdf-1.0.7.dist-info/WHEEL
popdf-1.0.7.dist-info/entry_points.txt
popdf-1.0.7.dist-info/top_level.txt
popdf-1.0.7.dist-info/RECORD
