Metadata-Version: 2.1
Name: popdf
Version: 1.0.7
Summary: pip install popdf
Home-page: https://www.python-office.com/
Author: CoderWanFeng
Author-email: 1957875073@qq.com
License: MIT
Project-URL: Bug Tracker, https://github.com/CoderWanFeng/popdf/issues
Project-URL: Documentation, http://www.python-office.com/course-002/10-popdf/10-popdf.html
Project-URL: Source Code, https://github.com/CoderWanFeng/popdf
Platform: any
Requires-Python: >=3.7
License-File: LICENSE
Requires-Dist: PyPDF2
Requires-Dist: pdf2docx
Requires-Dist: PyMuPDF
Requires-Dist: poprogress
Requires-Dist: pofile
Requires-Dist: loguru
Requires-Dist: pillow
Requires-Dist: click
